kmeans_gpu/__init__.py
kmeans_gpu/kmeans.py
kmeans_gpu-0.0.5.dist-info/LICENSE
kmeans_gpu-0.0.5.dist-info/METADATA
kmeans_gpu-0.0.5.dist-info/WHEEL
kmeans_gpu-0.0.5.dist-info/top_level.txt
kmeans_gpu-0.0.5.dist-info/RECORD
