Metadata-Version: 2.1
Name: kmeans-gpu
Version: 0.0.5
Summary: KMeans-GPU: A PyTorch Module for KMeans.
Home-page: https://github.com/densechen/kmeans-gpu
Author: densechen
Author-email: densechen@foxmail.com
License: MIT License
Download-URL: https://github.com/densechen/kmeans-gpu/archive/main.zip
Platform: UNKNOWN
Classifier: License :: OSI Approved :: MIT License
Classifier: Natural Language :: English
Classifier: Operating System :: OS Independent
Classifier: Programming Language :: Python :: 3.7
Classifier: Programming Language :: Python :: 3.8
Classifier: Programming Language :: Python :: 3.9
Classifier: Programming Language :: Python :: 3.10
Classifier: Topic :: Documentation :: Sphinx
Classifier: Topic :: Scientific/Engineering :: Artificial Intelligence
Classifier: Topic :: Software Development :: Libraries :: Python Modules
Requires-Python: >=3.7
Requires-Dist: torch
Requires-Dist: numpy
